automlkiller/__init__.py
automlkiller/classification.py
automlkiller/clustering.py
automlkiller/preprocessor.py
automlkiller/regression.py
automlkiller/reinforcementlearning.py
automlkiller/metrics/__init__.py
automlkiller/metrics/classification.py
automlkiller/models/__init__.py
automlkiller/models/classification.py
automlkiller/models/model_factory.py
automlkiller/models/classification/__init__.py
automlkiller/models/classification/adaboost_classifier.py
automlkiller/models/classification/catboost_classifier.py
automlkiller/models/classification/decisiontree_classifier.py
automlkiller/models/classification/extratrees_classifier.py
automlkiller/models/classification/gaussianNB_classifier.py
automlkiller/models/classification/gaussianprocessclassifier.py
automlkiller/models/classification/gradient_boosting_classifier.py
automlkiller/models/classification/kneighbors_classifier.py
automlkiller/models/classification/lgbm_classifier.py
automlkiller/models/classification/lineardiscriminantanalysis.py
automlkiller/models/classification/logisticregression.py
automlkiller/models/classification/mlpclassifier.py
automlkiller/models/classification/quadraticdiscriminantanalysis.py
automlkiller/models/classification/randomforest_classifier.py
automlkiller/models/classification/ridge_classifier.py
automlkiller/models/classification/sgd_classifier.py
automlkiller/models/classification/svc_classifier.py
automlkiller/models/classification/xgb_classifier.py
automlkiller/models/clustering/__init__.py
automlkiller/models/clustering/affinitypropagation_cluster.py
automlkiller/models/clustering/agglomerativeclustering_cluster.py
automlkiller/models/clustering/birch_cluster.py
automlkiller/models/clustering/dbscan_cluster.py
automlkiller/models/clustering/kmeans_cluster.py
automlkiller/models/clustering/kmodes_cluster.py
automlkiller/models/clustering/meanshift_cluster.py
automlkiller/models/clustering/optics_cluster.py
automlkiller/models/clustering/spectral_cluster.py
automlkiller-0.0.29.dist-info/LICENSE
automlkiller-0.0.29.dist-info/METADATA
automlkiller-0.0.29.dist-info/WHEEL
automlkiller-0.0.29.dist-info/top_level.txt
automlkiller-0.0.29.dist-info/RECORD
