Metadata-Version: 2.1
Name: automlkiller
Version: 0.0.29
Summary: Auto machine learning, deep learning library in Python.
Home-page: https://github.com/toandaominh1997/automlkiller
Author: toandaominh1997
Author-email: toandaominh1997@gmail.com
License: MIT
Platform: UNKNOWN
Classifier: License :: OSI Approved :: MIT License
Classifier: Programming Language :: Python :: 3.7
Classifier: Programming Language :: Python :: 3.8
Requires-Dist: numpy
Requires-Dist: pandas
Requires-Dist: matplotlib
Requires-Dist: tensorflow
Requires-Dist: tensorboard
Requires-Dist: torch
Requires-Dist: torchvision
Requires-Dist: seaborn
Requires-Dist: scikit-learn
Requires-Dist: pyod
Requires-Dist: category-encoders
Requires-Dist: xgboost
Requires-Dist: catboost
Requires-Dist: lightgbm
Requires-Dist: pandas-profiling
Requires-Dist: imbalanced-learn
Requires-Dist: scikit-plot
Requires-Dist: optuna
Requires-Dist: ray
Requires-Dist: tune-sklearn
Requires-Dist: yellowbrick
Requires-Dist: google-cloud-bigquery
Requires-Dist: google-cloud-storage
Requires-Dist: annoy
Requires-Dist: lightfm
